{
  "content_version": 2,
  "last_updated": "2026-03-05T00:00:00Z",
  "daily_question": {
    "id": 1,
    "title": "Historical Evidence for Pontius Pilate",
    "article_title": "The Pilate Stone",
    "options": [
      "The Pilate Stone",
      "An ancient myth invented in the Middle Ages",
      "A Roman political construct",
      "A commonly misunderstood geographical landmark"
    ],
    "correct_answer": "The Pilate Stone",
    "explanation": "Mind-Blowing Fact: The Pilate Stone\n\nUncovered in 1961 in Caesarea Maritima, it proved that Pontius Pilate was indeed the Roman prefect of Judaea.",
    "video_url": "https://www.youtube.com/watch?v=example",
    "video_title": "Archaeology of the Passion",
    "video_type": "YOUTUBE"
  }
}
